{
    "/css/springintoaction.onedrive.css": "/css/springintoaction.onedrive.css?id=fa4677f32f34928e540d",
    "/css/springintoaction.app.css": "/css/springintoaction.app.css?id=d421bf54be5d5653b59d",
    "/css/frontend/registration/springintoaction.app.css": "/css/frontend/registration/springintoaction.app.css?id=fc593c4f1baed9f57c13",
    "/css/springintoaction.fonts.css": "/css/springintoaction.fonts.css?id=b34dc9e7e6f8166387b8",
    "/css/springintoaction.frontend.css": "/css/springintoaction.frontend.css?id=fcaf8e37f04d2cd9767c",
    "/js/springintoaction.packages.js": "/js/springintoaction.packages.js?id=a381423460944dd08df8",
    "/js/springintoaction.packages.min.js": "/js/springintoaction.packages.min.js?id=cac1374cbf41022da1cb",
    "/js/springintoaction.models.js": "/js/springintoaction.models.js?id=faf86f507ee9110c15e5",
    "/js/springintoaction.collections.js": "/js/springintoaction.collections.js?id=ea15235683e52684140a",
    "/js/springintoaction.views.js": "/js/springintoaction.views.js?id=a2ac49e8ccbeb7784369",
    "/js/springintoaction.init.js": "/js/springintoaction.init.js?id=7dedf70e75b3c4edcb46",
    "/js/springintoaction.logging.js": "/js/springintoaction.logging.js?id=694852123351d75c0089",
    "/js/springintoaction.main.js": "/js/springintoaction.main.js?id=608d64146fa850ba115b",
    "/js/frontend/springintoaction.project-request.js": "/js/frontend/springintoaction.project-request.js?id=9c647a264dfee27d9303",
    "/js/frontend/springintoaction.project-registration.js": "/js/frontend/springintoaction.project-registration.js?id=d41d8cd98f00b204e980",
    "/js/frontend/registration/springintoaction.models.js": "/js/frontend/registration/springintoaction.models.js?id=c2619800b5546ab04537",
    "/js/frontend/registration/springintoaction.collections.js": "/js/frontend/registration/springintoaction.collections.js?id=dc91b3e81bc3a6566fa0",
    "/js/frontend/registration/springintoaction.views.js": "/js/frontend/registration/springintoaction.views.js?id=b7b5233d27541ec14c18",
    "/js/frontend/registration/springintoaction.init.js": "/js/frontend/registration/springintoaction.init.js?id=39c049f9de41e0b84d02",
    "/js/frontend/registration/springintoaction.main.js": "/js/frontend/registration/springintoaction.main.js?id=071536a997e3eec72b97",
    "/css/springintoaction.packages.css": "/css/springintoaction.packages.css?id=022055dbb9863723cc27",
    "/js/springintoaction.templates.js": "/js/springintoaction.templates.js?id=90bbed261b5995477abd",
    "/js/app-initial-models-vars-data.js": "/js/app-initial-models-vars-data.js?id=273dee48f94b181e107f",
    "/js/app-initial-collections-view-data.js": "/js/app-initial-collections-view-data.js?id=9da75be56dfb64c21f04",
    "/js/frontend/registration/springintoaction.templates.js": "/js/frontend/registration/springintoaction.templates.js?id=2b61ae43e99c5b097159",
    "/js/frontend/registration/app-initial-models-vars-data.js": "/js/frontend/registration/app-initial-models-vars-data.js?id=849699197969c57ed8dd",
    "/js/frontend/registration/app-initial-collections-view-data.js": "/js/frontend/registration/app-initial-collections-view-data.js?id=a2ea1fcf003cb8302442"
}
